Workbook

Sheet 汇总表
A1: xx远景项目成本汇总表
A3: 序号 | B3: 项目 | C3: 容量（Wp） | D3: 造价（元） | E3: 其中甲供（元） | F3: 备注
A5: 1 | B5: 光伏工程设备费 | C5: =光伏工程!M3 -> 26040 | D5: =光伏工程!J213 -> 176932
A6: 2 | B6: 储能工程设备费 | D6: =储能工程!J129 -> 186400 | E6: =储能工程!J5 -> 183400
A7: 3 | B7: 充电桩工程设备费 | D7: =充电桩工程!J71 -> 618300 | E7: =充电桩工程!J7+充电桩工程!J9 -> 598000
A8: 4 | B8: 建安费 | D8: =光伏工程!K213+光伏工程!L213+储能工程!K129+储能工程!L129+充电桩工程!K71+充电桩工程!L71 -> 668923.36 | F8: 考虑冬季施工，建安费用上调10%
A9: 5 | B9: 额外要求成本 | D9: =光伏工程!L224+储能工程!L137+充电桩工程!L73 -> 0
A10: 6 | B10: 勘察设计费 | D10: =SUM(光伏工程!L215:L217) -> 30000 | F10: 含荷载报告
A11: 7 | B11: 手续费 | D11: =SUM(光伏工程!L219:L222) -> 50000 | F11: 含接入手续办理及并网验收费用
A12: 8 | B12: 安措费 | D12: =D8*3% -> 20067.701 | F12: 安措费=（序号4）*3%
A13: 9 | B13: 财务费用 | D13: 0 | F13: 根据业务模式计算
A14: 10 | B14: EPC管理费及利润 | D14: =(SUM(D5:D8)-SUM(E5:E8))*6% -> 52149.322 | F14: 管理及利润=（序号1234）*6%，不含甲供材料
A15: 11 | B15: 工程保险费 | D15: =SUM(D5:D14)*0.0005+1000000*0.0015+900*10*C5/1000000 -> 2635.7462 | F15: 工程一切险，第三者责任险，承包商雇员险
A16: 12 | B16: 不可预见费 | D16: =SUM(D5:D15)*1.5% -> 27081.122 | F16: 不可预见费=（序号123456789）*1.5%，含甲供材料
B17: 合计 | D17: =SUM(D5:D16) -> 1832489.3 | E17: =SUM(E5:E16) -> 781400
B18: 每Wp造价 | D18: =D17/C5 -> 70.372091 | E18: =E17/C5 -> 30.00768

Sheet 光伏工程
A1: 光伏工程
A2: 分类 | B2: 序号 | C2: 项目名称 | D2: 特征描述 | E2: 单位 | F2: 工程量 | G2: 综合单价 | J2: 合价 | M2: 容量 | N2: 综合单价系数
G3: 设备费 | H3: 主材费 | I3: 建安费 | J3: 设备费 | K3: 主材费 | L3: 建安费 | M3: =F6*620 -> 26040 | N3: =1.1*1 -> 1.1
A4: 光伏设备及建安成本 | B4: 1 | C4: 光伏阵列
B5: 1.1 | C5: 光伏组件及安装
D6: 组件功率：620Wp（TOPCon一线） | E6: 块 | F6: 42 | G6: =0.8*620 -> 496 | I6: =22*$N$3 -> 24.2 | J6: =F6*G6 -> 20832 | L6: =F6*I6 -> 1016.4
D7: 组件功率：Wp（BC一线） | E7: 块 | G7: =(0.67+0.05)*600 -> 432 | I7: =22*$N$3 -> 24.2 | J7: =F7*G7 -> 0 | L7: =F7*I7 -> 0
B8: 1.2 | C8: 组件排泥器 | E8: 个 | F8: 84 | I8: =1.8*$N$3 -> 1.98 | L8: =F8*I8 -> 166.32
B9: 1.3 | C9: MC4接头 | D9: 组件串*4 | E9: 套 | F9: 10 | I9: =2.7*$N$3 -> 2.97 | L9: =F9*I9 -> 29.7
B10: 2 | C10: 变配电装置
B11: 2.1 | C11: 逆变器
C12: 组串逆变器 | D12: 华为50KW | E12: 台 | G12: 8400 | I12: =1000*$N$3 -> 1100 | J12: =F12*G12 -> 0 | L12: =F12*I12 -> 0
C13: 组串逆变器 | D13: 华为100KW | E13: 台 | G13: 18600 | I13: =1000*$N$3 -> 1100 | J13: =F13*G13 -> 0 | L13: =F13*I13 -> 0
C14: 组串逆变器 | D14: 华为110KW | E14: 台 | G14: 18600 | I14: =1000*$N$3 -> 1100 | J14: =F14*G14 -> 0 | L14: =F14*I14 -> 0
C15: 组串逆变器 | D15: 华为150KW | E15: 台 | G15: 22100 | I15: =1000*$N$3 -> 1100 | J15: =F15*G15 -> 0 | L15: =F15*I15 -> 0
C16: 组串逆变器 | D16: 华为300KW | E16: 台 | G16: 32900 | I16: =1000*$N$3 -> 1100 | J16: =F16*G16 -> 0 | L16: =F16*I16 -> 0
C17: 组串逆变器 | D17: 阳光30kW | E17: 台 | F17: 1 | G17: 4800 | I17: =1000*$N$3 -> 1100 | J17: =F17*G17 -> 4800 | L17: =F17*I17 -> 1100
C18: 组串逆变器 | D18: 阳光110kW | E18: 台 | G18: 16520 | I18: =1000*$N$3 -> 1100 | J18: =F18*G18 -> 0 | L18: =F18*I18 -> 0
C19: 组串逆变器 | D19: 阳光150kW | E19: 台 | G19: 20250 | I19: =1000*$N$3 -> 1100 | J19: =F19*G19 -> 0 | L19: =F19*I19 -> 0
C20: 组串逆变器 | D20: 阳光250kW | E20: 台 | G20: 21100 | I20: =1000*$N$3 -> 1100 | J20: =F20*G20 -> 0 | L20: =F20*I20 -> 0
C21: 组串逆变器 | D21: 阳光320kW | E21: 台 | G21: 33400 | I21: =1000*$N$3 -> 1100 | J21: =F21*G21 -> 0 | L21: =F21*I21 -> 0
C22: 组串逆变器 | D22: 锦浪50KW | E22: 台 | G22: 6400 | I22: =1000*$N$3 -> 1100 | J22: =F22*G22 -> 0 | L22: =F22*I22 -> 0
C23: 组串逆变器 | D23: 锦浪100KW | E23: 台 | G23: 14600 | I23: =1000*$N$3 -> 1100 | J23: =F23*G23 -> 0 | L23: =F23*I23 -> 0
C24: 组串逆变器 | D24: 锦浪150KW | E24: 台 | G24: 20000 | I24: =1000*$N$3 -> 1100 | J24: =F24*G24 -> 0 | L24: =F24*I24 -> 0
C25: 组串逆变器 | D25: 锦浪320kW | E25: 台 | G25: 32560 | I25: =1000*$N$3 -> 1100 | J25: =F25*G25 -> 0 | L25: =F25*I25 -> 0
B26: 2.2 | C26: 箱变
C27: 欧式箱变 | D27: SCB12-800/10.5/0.5kV （铜绕组，高压侧为负荷开关+熔断器） | E27: 台 | F27: 1 | G27: 149000 | I27: =3000*$N$3 -> 3300 | J27: =F27*G27 -> 149000 | L27: =F27*I27 -> 3300 | M27: 备注：升级为2级能耗，在此价格基础上加4万，高压侧升级为断路器方案，在此价格上加3万，高压侧升级环网柜方案，在此基础上加6万。
C28: 新增箱变对端侧改造 | F28: 1 | I28: 50000 | J28: =F28*G28 -> 0 | L28: =F28*I28 -> 50000
C29: 欧式箱变 | D29: SCB12-1000/10.5/0.9kV（铜绕组，高压侧为负荷开关+熔断器） | E29: 台 | G29: 185000 | I29: =3000*$N$3 -> 3300 | J29: =F29*G29 -> 0 | L29: =F29*I29 -> 0
C30: 欧式箱变 | D30: SCB12-1250/10.5/0.10kV（铜绕组，高压侧为负荷开关+熔断器） | E30: 台 | G30: 210000 | I30: =3000*$N$3 -> 3300 | J30: =F30*G30 -> 0 | L30: =F30*I30 -> 0
C31: 欧式箱变 | D31: SCB12-1600/10.5/0.11kV（铜绕组，高压侧为负荷开关+熔断器） | E31: 台 | G31: 255000 | I31: =3000*$N$3 -> 3300 | J31: =F31*G31 -> 0 | L31: =F31*I31 -> 0
C32: 欧式箱变 | D32: SCB12-2000/10.5/0.12kV（铜绕组，高压侧为负荷开关+熔断器） | E32: 台 | G32: 275000 | I32: =3000*$N$3 -> 3300 | J32: =F32*G32 -> 0 | L32: =F32*I32 -> 0
C33: 欧式箱变 | D33: SCB12-2500/10.5/0.13kV（铜绕组，高压侧为负荷开关+熔断器） | E33: 台 | G33: 305000 | I33: =3000*$N$3 -> 3300 | J33: =F33*G33 -> 0 | L33: =F33*I33 -> 0
C34: 欧式箱变 | D34: SCB12-3150/10.5/0.14kV（铜绕组，高压侧为负荷开关+熔断器） | E34: 台 | G34: 325000 | I34: =3000*$N$3 -> 3300 | J34: =F34*G34 -> 0 | L34: =F34*I34 -> 0
B35: 2.3 | C35: 开关柜
D36: 10kV 并网柜（KYN28A-12，Ir=630A,Ib=25kA) | E36: 面 | G36: 52000 | I36: =1000*$N$3 -> 1100 | J36: =F36*G36 -> 0 | L36: =F36*I36 -> 0
D37: 10kV 出线柜（KYN28A-12，Ir=630A,Ib=25kA） | E37: 面 | G37: 52000 | I37: =1000*$N$3 -> 1100 | J37: =F37*G37 -> 0 | L37: =F37*I37 -> 0
D38: 10KV PT柜（KYN28A-12，Ib=25kA） | E38: 面 | G38: 30340 | I38: =1000*$N$3 -> 1100 | J38: =F38*G38 -> 0 | L38: =F38*I38 -> 0
D39: 10KV 计量柜（KYN28A-12，Ir=630A,Ib=25kA） | E39: 面 | G39: 25000 | I39: =1000*$N$3 -> 1100 | J39: =F39*G39 -> 0 | L39: =F39*I39 -> 0
D40: 10KV SVG柜（KYN28A-12，Ir=630A,Ib=25kA） | E40: 面 | G40: 50800 | I40: =1000*$N$3 -> 1100 | J40: =F40*G40 -> 0 | L40: =F40*I40 -> 0
D41: 10KV 光伏集电线柜（KYN28A-12，Ir=630A,Ib=25kA） | E41: 面 | G41: 52000 | I41: =1000*$N$3 -> 1100 | J41: =F41*G41 -> 0 | L41: =F41*I41 -> 0
D42: 10kv 站用变柜（KYN28A-12，Ir=630A,Ib=25kA） | E42: 面 | G42: 40000 | I42: =1000*$N$3 -> 1100 | J42: =F42*G42 -> 0 | L42: =F42*I42 -> 0
D43: 400V 并网柜（GGD柜，国内一线框架断路器630A） | E43: 面 | G43: 18000 | I43: =1000*$N$3 -> 1100 | J43: =F43*G43 -> 0 | L43: =F43*I43 -> 0
D44: 400V 并网柜（GGD柜，国内一线框架断路器1250A） | E44: 面 | G44: 20000 | I44: =1000*$N$3 -> 1100 | J44: =F44*G44 -> 0 | L44: =F44*I44 -> 0
D45: 400V 并网柜（GGD柜，ABB框架断路器1250A） | E45: 面 | G45: 30000 | I45: =1000*$N$3 -> 1100 | J45: =F45*G45 -> 0 | L45: =F45*I45 -> 0
B46: 2.4 | C46: SVG设备
C47: 10kV 直挂SVG | D47: ±0.5Mvar | E47: 台 | G47: 180000 | I47: =2000*$N$3 -> 2200 | J47: =F47*G47 -> 0 | L47: =F47*I47 -> 0
C48: 10kV 直挂SVG | D48: ±1Mvar | E48: 台 | G48: 208000 | I48: =2000*$N$3 -> 2200 | J48: =F48*G48 -> 0 | L48: =F48*I48 -> 0
C49: 10kV 直挂SVG | D49: ±1.5Mvar | E49: 台 | G49: 213000 | I49: =2000*$N$3 -> 2200 | J49: =F49*G49 -> 0 | L49: =F49*I49 -> 0
C50: 10kV 直挂SVG | D50: ±2Mvar | E50: 台 | G50: 220000 | I50: =2000*$N$3 -> 2200 | J50: =F50*G50 -> 0 | L50: =F50*I50 -> 0
C51: 400V 电容柜 | D51: GGD柜 ,600kvar | E51: 台 | G51: 30000 | I51: =1000*$N$3 -> 1100 | J51: =F51*G51 -> 0 | L51: =F51*I51 -> 0
C52: 四象限无功补偿控制器 | D52: 400V | E52: 点 | G52: 700 | I52: =2000*$N$3 -> 2200 | J52: =F52*G52 -> 0 | L52: =F52*I52 -> 0
B53: 2.5 | C53: 站用电
C54: 10kv站用变 | D54: 50KVA | E54: 台 | G54: 20000 | I54: =2000*$N$3 -> 2200 | J54: =F54*G54 -> 0 | L54: =F54*I54 -> 0
C55: 低压站用柜 | D55: GGD柜 ,双电源供电 | E55: 面 | G55: 20000 | I55: =1000*$N$3 -> 1100 | J55: =F55*G55 -> 0 | L55: =F55*I55 -> 0
B56: 2.6 | C56: 预制舱
C57: 一次预制舱 | D57: 6.5*3.5*3 | E57: 台 | G57: =6.5*3.5*3000 -> 68250 | I57: =5000*$N$3 -> 5500 | J57: =F57*G57 -> 0 | L57: =F57*I57 -> 0
C58: 二次预制舱 | D58: 6*3.5*3 | E58: 台 | G58: =6*3.5*3000 -> 63000 | I58: =5000*$N$3 -> 5500 | J58: =F58*G58 -> 0 | L58: =F58*I58 -> 0
C59: 一二次预制舱 | D59: 9.5*3.5*3 | E59: 台 | G59: =9.5*3.5*3000 -> 99750 | I59: =10000*$N$3 -> 11000 | J59: =F59*G59 -> 0 | L59: =F59*I59 -> 0
B60: 3 | C60: 电气二次
B61: 3.1 | C61: 10kV并网
C62: 计算机监控系统 | E62: 套 | G62: 55000 | I62: =1000*$N$3 -> 1100 | J62: =F62*G62 -> 0 | L62: =F62*I62 -> 0
C63: 远动通讯屏 | D63: 包括远动通信装置、对时装置 | E63: 套 | G63: 45000 | I63: =1000*$N$3 -> 1100 | J63: =F63*G63 -> 0 | L63: =F63*I63 -> 0
C64: 综合解列装置柜 | D64: 包括防孤岛保护装置，公用测控装置，电能质量在线监测装置 | E64: 套 | G64: 55800 | I64: =1000*$N$3 -> 1100 | J64: =F64*G64 -> 0 | L64: =F64*I64 -> 0
C65: 交直流一体化电源系统 | E65: 面 | G65: 89000 | I65: =1000*$N$3 -> 1100 | J65: =F65*G65 -> 0 | L65: =F65*I65 -> 0
C66: 环境检测仪 | E66: 套 | G66: 15000 | I66: =1000*$N$3 -> 1100 | J66: =F66*G66 -> 0 | L66: =F66*I66 -> 0
C67: 有功无功控制系统 | E67: 套 | G67: 115000 | I67: =1000*$N$3 -> 1100 | J67: =F67*G67 -> 0 | L67: =F67*I67 -> 0
C68: 调度通信系统 | D68: 无线传输终端（带4G卡） | E68: 套 | G68: 50000 | I68: =1000*$N$3 -> 1100 | J68: =F68*G68 -> 0 | L68: =F68*I68 -> 0
C69: 调度通信系统 | D69: 有线 | E69: 套 | G69: 50000 | I69: =1000*$N$3 -> 1100 | J69: =F69*G69 -> 0 | L69: =F69*I69 -> 0
C70: 保护测控装置 | D70: 安装在开关柜上 | E70: 套 | G70: 7000 | I70: =1000*$N$3 -> 1100 | J70: =F70*G70 -> 0 | L70: =F70*I70 -> 0
C71: 光纤差动保护测控装置 | D71: 安装在开关柜上 | E71: 套 | G71: 15000 | I71: =1000*$N$3 -> 1100 | J71: =F71*G71 -> 0 | L71: =F71*I71 -> 0
C72: 负荷控制装置 | E72: 套 | G72: 20000 | I72: =1000*$N$3 -> 1100 | J72: =F72*G72 -> 0 | L72: =F72*I72 -> 0
C73: 电能量采集终端 | E73: 套 | G73: 8000 | I73: =300*$N$3 -> 330 | J73: =F73*G73 -> 0 | L73: =F73*I73 -> 0
C74: 关口计量表 | D74: 0.2S级计量表（就地安装在开关柜上） | E74: 套 | F74: 1 | G74: 2300 | I74: =100*$N$3 -> 110 | J74: =F74*G74 -> 2300 | L74: =F74*I74 -> 110
C75: 电度表 | D75: 0.5S级考核表（进线柜、出线柜） | E75: 台 | G75: 1300 | I75: =100*$N$3 -> 110 | J75: =F75*G75 -> 0 | L75: =F75*I75 -> 0
C76: 视频监控系统 | E76: 项 | G76: 30000 | I76: =1000*$N$3 -> 1100 | J76: =F76*G76 -> 0 | L76: =F76*I76 -> 0
C77: 视频摄像头 | D77: 含立杆，电源箱,4G卡等 | E77: 套 | G77: 4000 | I77: =500*$N$3 -> 550 | J77: =F77*G77 -> 0 | L77: =F77*I77 -> 0
C78: RS485通讯线 | E78: m | F78: 50 | H78: =5*$N$3 -> 5.5 | I78: =5*$N$3 -> 5.5 | K78: =F78*H78 -> 275 | L78: =F78*I78 -> 275
C79: 超五类网络线 | E79: m | H79: =5*$N$3 -> 5.5 | I79: =5*$N$3 -> 5.5 | K79: =F79*H79 -> 0 | L79: =F79*I79 -> 0
C80: 单模光纤 | D80: 24芯 | E80: m | H80: =5*$N$3 -> 5.5 | I80: =5*$N$3 -> 5.5 | K80: =F80*H80 -> 0 | L80: =F80*I80 -> 0
C81: 控制电缆 | D81: ZC-KVVP22-0.45/0.75kV-4×2.5 | E81: m | H81: =12.76*$N$3 -> 14.036 | I81: =5*$N$3 -> 5.5 | K81: =F81*H81 -> 0 | L81: =F81*I81 -> 0
B82: 3.2 | C82: 400V并网
C83: 防过载防逆流电表 | E83: 套 | G83: 1500 | I83: =500*$N$3 -> 550 | J83: =F83*G83 -> 0 | L83: =F83*I83 -> 0
C84: 防逆流装置 | E84: 套 | G84: 5000 | I84: =1000*$N$3 -> 1100 | J84: =F84*G84 -> 0 | L84: =F84*I84 -> 0
C85: 防孤岛模块 | D85: 400V | E85: 套 | G85: 20000 | I85: =1000*$N$3 -> 1100 | J85: =F85*G85 -> 0 | L85: =F85*I85 -> 0
C86: 环境检测仪 | E86: 套 | G86: 15000 | I86: =1000*$N$3 -> 1100 | J86: =F86*G86 -> 0 | L86: =F86*I86 -> 0
C87: 电能质量在线监测装置 | E87: 套 | G87: 6000 | I87: =1000*$N$3 -> 1100 | J87: =F87*G87 -> 0 | L87: =F87*I87 -> 0
C88: 视频监控系统 | E88: 项 | G88: 30000 | I88: =1000*$N$3 -> 1100 | J88: =F88*G88 -> 0 | L88: =F88*I88 -> 0
C89: 视频摄像头 | D89: 含立杆，电源箱,4G卡等 | E89: 套 | G89: 4000 | I89: =500*$N$3 -> 550 | J89: =F89*G89 -> 0 | L89: =F89*I89 -> 0
C90: 关口计量表 | D90: 0.2S级计量表 | E90: 套 | G90: 2300 | I90: =100*$N$3 -> 110 | J90: =F90*G90 -> 0 | L90: =F90*I90 -> 0
C91: RS485通讯线 | E91: m | H91: =5*$N$3 -> 5.5 | I91: =5*$N$3 -> 5.5 | K91: =F91*H91 -> 0 | L91: =F91*I91 -> 0
C92: 超五类网络线 | E92: m | H92: =5*$N$3 -> 5.5 | I92: =5*$N$3 -> 5.5 | K92: =F92*H92 -> 0 | L92: =F92*I92 -> 0
B93: 3.3 | C93: 平台数据接入系统
C94: ENOS平台数据接入系统 | D94: 远景智能 | E94: 套 | G94: 123500 | J94: =F94*G94 -> 0
C95: ENOS平台数据接入系统 | D95: 长园深瑞（含接入人工费） | E95: 套 | G95: 60000 | J95: =F95*G95 -> 0
B96: 4 | C96: 集电线路
B97: 4.1 | C97: 直流电缆
D98: H1Z2Z2-K-1*4mm² | E98: km | F98: 0.44 | H98: =4.5*1000*$N$3 -> 4950 | I98: =2000*$N$3 -> 2200 | K98: =F98*H98 -> 2178 | L98: =F98*I98 -> 968
D99: H1Z2Z2-K-1*6mm² | E99: km | H99: =6.68*1000*$N$3 -> 7348 | I99: =2000*$N$3 -> 2200 | K99: =F99*H99 -> 0 | L99: =F99*I99 -> 0
B100: 4.2 | C100: 低压交流电力电缆
...

Sheet 储能工程
A1: 储能工程
A2: 分类 | B2: 序号 | C2: 项目名称 | D2: 特征描述 | E2: 单位 | F2: 工程量 | G2: 综合单价 | J2: 合价 | M2: 综合单价系数
G3: 设备费 | H3: 主材费 | I3: 建安费 | J3: 设备费 | K3: 主材费 | L3: 建安费 | M3: =1.1*1 -> 1.1
A4: 储能设备及建安成本 | B4: 1 | C4: 储能柜
B5: 1.1 | C5: 储能柜及安装 | D5: 125KW/262kWh | E5: 台 | F5: 1 | G5: =262000*0.7 -> 183400 | I5: =2000*$M$3 -> 2200 | J5: =F5*G5 -> 183400 | L5: =F5*I5 -> 2200
B6: 2 | C6: 变配电装置
B7: 2.1 | C7: 箱变
C8: 欧式箱变 | D8: SCB12-800/10.5/0.8kV （铜绕组，高压侧为负荷开关+熔断器） | E8: 台 | G8: 169000 | I8: =3000*$M$3 -> 3300 | J8: =F8*G8 -> 0 | L8: =F8*I8 -> 0
D9: SCB12-1000/10.5/0.9kV（铜绕组，高压侧为负荷开关+熔断器） | E9: 台 | G9: 185000 | I9: =3000*$M$3 -> 3300 | J9: =F9*G9 -> 0 | L9: =F9*I9 -> 0
D10: SCB12-1250/10.5/0.10kV（铜绕组，高压侧为负荷开关+熔断器） | E10: 台 | G10: 210000 | I10: =3000*$M$3 -> 3300 | J10: =F10*G10 -> 0 | L10: =F10*I10 -> 0
D11: SCB12-1600/10.5/0.11kV（铜绕组，高压侧为负荷开关+熔断器） | E11: 台 | G11: 255000 | I11: =3000*$M$3 -> 3300 | J11: =F11*G11 -> 0 | L11: =F11*I11 -> 0
D12: SCB12-2000/10.5/0.12kV（铜绕组，高压侧为负荷开关+熔断器） | E12: 台 | G12: 275000 | I12: =3000*$M$3 -> 3300 | J12: =F12*G12 -> 0 | L12: =F12*I12 -> 0
D13: SCB12-2500/10.5/0.13kV（铜绕组，高压侧为负荷开关+熔断器） | E13: 台 | G13: 305000 | I13: =3000*$M$3 -> 3300 | J13: =F13*G13 -> 0 | L13: =F13*I13 -> 0
D14: SCB12-3150/10.5/0.14kV（铜绕组，高压侧为负荷开关+熔断器） | E14: 台 | G14: 325000 | I14: =3000*$M$3 -> 3300 | J14: =F14*G14 -> 0 | L14: =F14*I14 -> 0
B15: 2.2 | C15: 开关柜
D16: 10kV 并网柜（KYN28A-12，Ir=630A,Ib=25kA) | E16: 面 | G16: 52000 | I16: =1000*$M$3 -> 1100 | J16: =F16*G16 -> 0 | L16: =F16*I16 -> 0
D17: 10kV 出线柜（KYN28A-12，Ir=630A,Ib=25kA） | E17: 面 | G17: 52000 | I17: =1000*$M$3 -> 1100 | J17: =F17*G17 -> 0 | L17: =F17*I17 -> 0
D18: 10KV PT柜（KYN28A-12，Ib=25kA） | E18: 面 | G18: 30340 | I18: =1000*$M$3 -> 1100 | J18: =F18*G18 -> 0 | L18: =F18*I18 -> 0
D19: 10KV 计量柜（KYN28A-12，Ir=630A,Ib=25kA） | E19: 面 | G19: 25000 | I19: =1000*$M$3 -> 1100 | J19: =F19*G19 -> 0 | L19: =F19*I19 -> 0
D20: 10KV SVG柜（KYN28A-12，Ir=630A,Ib=25kA） | E20: 面 | G20: 50800 | I20: =1000*$M$3 -> 1100 | J20: =F20*G20 -> 0 | L20: =F20*I20 -> 0
D21: 10KV 光伏集电线柜（KYN28A-12，Ir=630A,Ib=25kA） | E21: 面 | G21: 52000 | I21: =1000*$M$3 -> 1100 | J21: =F21*G21 -> 0 | L21: =F21*I21 -> 0
D22: 10kv 站用变柜（KYN28A-12，Ir=630A,Ib=25kA） | E22: 面 | G22: 40000 | I22: =1000*$M$3 -> 1100 | J22: =F22*G22 -> 0 | L22: =F22*I22 -> 0
D23: 400V 并网柜（GGD柜，国内一线框架断路器630A） | E23: 面 | G23: 20000 | I23: =1000*$M$3 -> 1100 | J23: =F23*G23 -> 0 | L23: =F23*I23 -> 0
D24: 400V 并网柜（GGD柜，国内一线框架断路器1250A） | E24: 面 | G24: 25000 | I24: =1000*$M$3 -> 1100 | J24: =F24*G24 -> 0 | L24: =F24*I24 -> 0
D25: 400V 并网柜（GGD柜，ABB框架断路器1250A） | E25: 面 | G25: 35000 | I25: =1000*$M$3 -> 1100 | J25: =F25*G25 -> 0 | L25: =F25*I25 -> 0
B26: 2.3 | C26: SVG设备
C27: 10kV 直挂SVG | D27: ±0.5Mvar | E27: 台 | G27: 180000 | I27: =2000*$M$3 -> 2200 | J27: =F27*G27 -> 0 | L27: =F27*I27 -> 0
D28: ±1Mvar | E28: 台 | G28: 208000 | I28: =2000*$M$3 -> 2200 | J28: =F28*G28 -> 0 | L28: =F28*I28 -> 0
D29: ±1.5Mvar | E29: 台 | G29: 213000 | I29: =2000*$M$3 -> 2200 | J29: =F29*G29 -> 0 | L29: =F29*I29 -> 0
D30: ±2Mvar | E30: 台 | G30: 220000 | I30: =2000*$M$3 -> 2200 | J30: =F30*G30 -> 0 | L30: =F30*I30 -> 0
C31: 400V 电容柜 | D31: GGD柜 ,600kvar | E31: 台 | G31: 30000 | I31: =1000*$M$3 -> 1100 | J31: =F31*G31 -> 0 | L31: =F31*I31 -> 0
B32: 2.4 | C32: 站用电
C33: 10kv站用变 | D33: 50KVA | E33: 台 | G33: 20000 | I33: =2000*$M$3 -> 2200 | J33: =F33*G33 -> 0 | L33: =F33*I33 -> 0
C34: 低压站用柜 | D34: GGD柜 ,双电源供电 | E34: 面 | G34: 20000 | I34: =1000*$M$3 -> 1100 | J34: =F34*G34 -> 0 | L34: =F34*I34 -> 0
B35: 2.5 | C35: 预制舱
C36: 一次预制舱 | D36: 6.5*3.5*3 | E36: 台 | G36: =6.5*3.5*3000 -> 68250 | I36: =5000*$M$3 -> 5500 | J36: =F36*G36 -> 0 | L36: =F36*I36 -> 0
C37: 二次预制舱 | D37: 6*3.5*3 | E37: 台 | G37: =6*3.5*3000 -> 63000 | I37: =5000*$M$3 -> 5500 | J37: =F37*G37 -> 0 | L37: =F37*I37 -> 0
C38: 一二次预制舱 | D38: 9.5*3.5*3 | E38: 台 | G38: =9.5*3.5*3000 -> 99750 | I38: =10000*$M$3 -> 11000 | J38: =F38*G38 -> 0 | L38: =F38*I38 -> 0
B39: 3 | C39: 电气二次
B40: 3.1 | C40: 10kV并网
C41: 计算机监控系统 | E41: 套 | G41: 60900 | I41: =1000*$M$3 -> 1100 | J41: =F41*G41 -> 0 | L41: =F41*I41 -> 0
C42: 远动通讯屏 | D42: 包括远动通信装置、对时装置 | E42: 套 | G42: 45500 | I42: =1000*$M$3 -> 1100 | J42: =F42*G42 -> 0 | L42: =F42*I42 -> 0
C43: 综合解列装置柜 | D43: 包括防孤岛保护装置，公用测控装置，电能质量在线监测装置 | E43: 套 | G43: 66800 | I43: =1000*$M$3 -> 1100 | J43: =F43*G43 -> 0 | L43: =F43*I43 -> 0
C44: 交直流一体化电源系统 | E44: 面 | G44: 109000 | I44: =1000*$M$3 -> 1100 | J44: =F44*G44 -> 0 | L44: =F44*I44 -> 0
C45: 环境检测仪 | E45: 套 | G45: 20000 | I45: =1000*$M$3 -> 1100 | J45: =F45*G45 -> 0 | L45: =F45*I45 -> 0
C46: 有功无功控制系统 | E46: 套 | G46: 115000 | I46: =1000*$M$3 -> 1100 | J46: =F46*G46 -> 0 | L46: =F46*I46 -> 0
C47: 调度通信系统 | D47: 无线传输终端（带4G卡） | E47: 套 | G47: 50000 | I47: =1000*$M$3 -> 1100 | J47: =F47*G47 -> 0 | L47: =F47*I47 -> 0
C48: 保护测控装置 | D48: 安装在开关柜上 | E48: 套 | G48: 7000 | I48: =1000*$M$3 -> 1100 | J48: =F48*G48 -> 0 | L48: =F48*I48 -> 0
C49: 光纤差动保护测控装置 | D49: 安装在开关柜上 | E49: 套 | G49: 15000 | I49: =1000*$M$3 -> 1100 | J49: =F49*G49 -> 0 | L49: =F49*I49 -> 0
C50: 电能量采集终端 | E50: 套 | G50: 8000 | I50: =300*$M$3 -> 330 | J50: =F50*G50 -> 0 | L50: =F50*I50 -> 0
C51: 关口计量表 | D51: 0.2S级计量表（就地安装在开关柜上） | E51: 套 | G51: 2300 | I51: =100*$M$3 -> 110 | J51: =F51*G51 -> 0 | L51: =F51*I51 -> 0
C52: 电度表 | D52: 0.5S级考核表（进线柜、出线柜） | E52: 台 | G52: 1300 | I52: =100*$M$3 -> 110 | J52: =F52*G52 -> 0 | L52: =F52*I52 -> 0
C53: 视频监控系统 | E53: 项 | G53: 30000 | I53: =1000*$M$3 -> 1100 | J53: =F53*G53 -> 0 | L53: =F53*I53 -> 0
C54: 视频摄像头 | D54: 含立杆，电源箱,4G卡等 | E54: 套 | G54: 4000 | I54: =500*$M$3 -> 550 | J54: =F54*G54 -> 0 | L54: =F54*I54 -> 0
C55: RS485通讯线 | E55: m | F55: 50 | H55: =5*$M$3 -> 5.5 | I55: =5*$M$3 -> 5.5 | K55: =F55*H55 -> 275 | L55: =F55*I55 -> 275
C56: 超五类网络线 | E56: m | H56: =5*$M$3 -> 5.5 | I56: =5*$M$3 -> 5.5 | K56: =F56*H56 -> 0 | L56: =F56*I56 -> 0
C57: 单模光纤 | D57: 24芯 | E57: m | H57: =5*$M$3 -> 5.5 | I57: =5*$M$3 -> 5.5 | K57: =F57*H57 -> 0 | L57: =F57*I57 -> 0
C58: 控制电缆 | D58: ZC-KVVP22-0.45/0.75kV-4×2.5 | E58: m | H58: =12.76*$M$3 -> 14.036 | I58: =5*$M$3 -> 5.5 | K58: =F58*H58 -> 0 | L58: =F58*I58 -> 0
B59: 3.2 | C59: 400V并网
C60: 防过载防逆流电表 | E60: 套 | F60: 2 | G60: 1500 | I60: =500*$M$3 -> 550 | J60: =F60*G60 -> 3000 | L60: =F60*I60 -> 1100
C61: 防逆流装置 | E61: 套 | G61: 5000 | I61: =1000*$M$3 -> 1100 | J61: =F61*G61 -> 0 | L61: =F61*I61 -> 0
C62: 防孤岛模块 | D62: 400V | E62: 套 | G62: 20000 | I62: =1000*$M$3 -> 1100 | J62: =F62*G62 -> 0 | L62: =F62*I62 -> 0
C63: 视频监控系统 | E63: 项 | G63: 30000 | I63: =1000*$M$3 -> 1100 | J63: =F63*G63 -> 0 | L63: =F63*I63 -> 0
C64: 视频摄像头 | D64: 含立杆，电源箱,4G卡等 | E64: 套 | G64: 4000 | I64: =500*$M$3 -> 550 | J64: =F64*G64 -> 0 | L64: =F64*I64 -> 0
B65: 3.3 | C65: ENOS平台数据接入系统 | D65: 远景智能品牌（甲指乙采） | E65: 套 | G65: 123500 | J65: =F65*G65 -> 0
B66: 4 | C66: 集电线路
B67: 4.1 | C67: 低压交流电力电缆
D68: ZC-YJV22-0.6/1kV-3×70mm²+1×35mm² | E68: m | H68: =203.59*$M$3 -> 223.949 | I68: =20*$M$3 -> 22 | K68: =F68*H68 -> 0 | L68: =F68*I68 -> 0
D69: ZC-YJV22-0.6/1kV-3×95mm²+1×50mm² | E69: m | H69: =281.67*$M$3 -> 309.837 | I69: =20*$M$3 -> 22 | K69: =F69*H69 -> 0 | L69: =F69*I69 -> 0
D70: ZC-YJV22-0.6/1kV-3×120mm²+1×70mm² | E70: m | H70: =361.65*$M$3 -> 397.815 | I70: =20*$M$3 -> 22 | K70: =F70*H70 -> 0 | L70: =F70*I70 -> 0
D71: ZC-YJV22-0.6/1kV-3×150mm²+1×70mm² | E71: m | H71: =427.5*$M$3 -> 470.25 | I71: =20*$M$3 -> 22 | K71: =F71*H71 -> 0 | L71: =F71*I71 -> 0
D72: ZC-YJHLV22-0.6/1kV-3×95mm²+1×50mm² | E72: m | H72: =38.33*$M$3 -> 42.163 | I72: =20*$M$3 -> 22 | K72: =F72*H72 -> 0 | L72: =F72*I72 -> 0
D73: ZC-YJLHV22-0.6/1kV-3×120mm²+1×70mm² | E73: m | F73: 20 | H73: =48.82*$M$3 -> 53.702 | I73: =20*$M$3 -> 22 | K73: =F73*H73 -> 1074.04 | L73: =F73*I73 -> 440
D74: ZC-YJLHV22-0.6/1kV-3×150mm²+1×70mm² | E74: m | H74: =55.9*$M$3 -> 61.49 | I74: =20*$M$3 -> 22 | K74: =F74*H74 -> 0 | L74: =F74*I74 -> 0
D75: ZC-YJLHV22-0.6/1kV 3×185mm²+1×95mm² | E75: m | H75: =68.89*$M$3 -> 75.779 | I75: =20*$M$3 -> 22 | K75: =F75*H75 -> 0 | L75: =F75*I75 -> 0
D76: ZC-YJLHV22-1.8/3kV-3×95mm² | E76: m | H76: =36.5*$M$3 -> 40.15 | I76: =20*$M$3 -> 22 | K76: =F76*H76 -> 0 | L76: =F76*I76 -> 0
D77: ZC-YJLHV22-1.8/3kV-3×120mm² | E77: m | H77: =43.82*$M$3 -> 48.202 | I77: =20*$M$3 -> 22 | K77: =F77*H77 -> 0 | L77: =F77*I77 -> 0
D78: ZC-YJLHV22-1.8/3kV-3×150mm² | E78: m | H78: =52.01*$M$3 -> 57.211 | I78: =20*$M$3 -> 22 | K78: =F78*H78 -> 0 | L78: =F78*I78 -> 0
D79: ZC-YJV22-1.8/3kV-3×95mm² | E79: m | H79: =246.16*$M$3 -> 270.776 | I79: =20*$M$3 -> 22 | K79: =F79*H79 -> 0 | L79: =F79*I79 -> 0
D80: ZC-YJV22-1.8/3kV-3×120mm² | E80: m | H80: =307.98*$M$3 -> 338.778 | I80: =20*$M$3 -> 22 | K80: =F80*H80 -> 0 | L80: =F80*I80 -> 0
D81: ZC-YJV22-1.8/3kV-3×150mm² | E81: m | H81: =375.97*$M$3 -> 413.567 | I81: =20*$M$3 -> 22 | K81: =F81*H81 -> 0 | L81: =F81*I81 -> 0
B82: 4.2 | C82: 高压电力电缆
D83: ZC-YJV22-8.7/15kV-3×95mm² | E83: m | H83: =283.5*$M$3 -> 311.85 | I83: =30*$M$3 -> 33 | K83: =F83*H83 -> 0 | L83: =F83*I83 -> 0
D84: ZC-YJV22-8.7/15kV-3×120mm² | E84: m | H84: =346.56*$M$3 -> 381.216 | I84: =30*$M$3 -> 33 | K84: =F84*H84 -> 0 | L84: =F84*I84 -> 0
D85: ZC-YJV22-8.7/15kV-3×150mm² | E85: m | H85: =414.05*$M$3 -> 455.455 | I85: =30*$M$3 -> 33 | K85: =F85*H85 -> 0 | L85: =F85*I85 -> 0
B86: 4.3 | C86: 电缆终端
C87: 中压电缆头 | D87: 10kV，户内冷缩 | E87: 套 | H87: =500*$M$3 -> 550 | I87: =200*$M$3 -> 220 | K87: =F87*H87 -> 0 | L87: =F87*I87 -> 0
C88: 低压电缆头 | E88: 套 | F88: 2 | H88: =200*$M$3 -> 220 | I88: =200*$M$3 -> 220 | K88: =F88*H88 -> 440 | L88: =F88*I88 -> 440
B89: 4.4 | C89: 电缆保护管
C90: 软管 | D90: Φ50*3.7 PE材质 | E90: m | H90: =3*$M$3 -> 3.3 | I90: =8*$M$3 -> 8.8 | K90: =F90*H90 -> 0 | L90: =F90*I90 -> 0
C91: 不锈钢管 | D91: SC100，4.5mm厚 | E91: m | H91: =190*$M$3 -> 209 | I91: =15*$M$3 -> 16.5 | K91: =F91*H91 -> 0 | L91: =F91*I91 -> 0
C92: 不锈钢管 | D92: SC150，4.5mm厚 | E92: m | H92: =280*$M$3 -> 308 | I92: =15*$M$3 -> 16.5 | K92: =F92*H92 -> 0 | L92: =F92*I92 -> 0
C93: 热镀锌钢管 | D93: φ50 | E93: m | H93: =32*$M$3 -> 35.2 | I93: =17*$M$3 -> 18.7 | K93: =F93*H93 -> 0 | L93: =F93*I93 -> 0
C94: 热镀锌钢管 | D94: φ100 | E94: m | F94: 15 | H94: =60*$M$3 -> 66 | I94: =28*$M$3 -> 30.8 | K94: =F94*H94 -> 990 | L94: =F94*I94 -> 462
C95: 热镀锌钢管 | D95: φ125 | E95: m | H95: =85*$M$3 -> 93.5 | I95: =32*$M$3 -> 35.2 | K95: =F95*H95 -> 0 | L95: =F95*I95 -> 0
C96: 热镀锌钢管 | D96: φ150 | E96: m | H96: =110*$M$3 -> 121 | I96: =37*$M$3 -> 40.7 | K96: =F96*H96 -> 0 | L96: =F96*I96 -> 0
B97: 5 | C97: 接地及辅材
B98: 5.1 | C98: 接地
C99: 接地扁铁 | D99: 40X4 | E99: m | F99: 20 | H99: =20*$M$3 -> 22 | I99: =10*$M$3 -> 11 | K99: =F99*H99 -> 440 | L99: =F99*I99 -> 220
C100: 接地扁铁 | D100: 50X5 | E100: m | H100: =24*$M$3 -> 26.4 | I100: =12*$M$3 -> 13.2 | K100: =F100*H100 -> 0 | L100: =F100*I100 -> 0
...

Sheet 充电桩工程
A1: 充电桩工程
A2: 分类 | B2: 序号 | C2: 项目名称 | D2: 特征描述 | E2: 单位 | F2: 工程量 | G2: 综合单价 | J2: 合价 | M2: 综合单价系数
G3: 设备费 | H3: 主材费 | I3: 建安费 | J3: 设备费 | K3: 主材费 | L3: 建安费 | M3: =1.05*1 -> 1.05
A4: 充电桩设备及建安成本 | B4: 1 | C4: 充电桩
B5: 1.1 | C5: 充电桩安装 | D5: 7kW交流充电桩 | E5: 台 | I5: =200*$M$3 -> 210 | J5: =F5*G5 -> 0 | L5: =F5*I5 -> 0
B6: 1.2 | C6: 充电桩安装 | D6: 60kW直流充电桩 | E6: 台 | I6: =500*$M$3 -> 525 | J6: =F6*G6 -> 0 | L6: =F6*I6 -> 0
B7: 1.3 | C7: 充电桩安装 | D7: 132kW直流充电桩 V2G | E7: 台 | F7: 1 | G7: 98000 | I7: =1000*$M$3 -> 1050 | J7: =F7*G7 -> 98000 | L7: =F7*I7 -> 1050
B8: 1.4 | C8: 充电桩安装 | D8: 240kW直流充电桩 | E8: 台 | I8: =2000*$M$3 -> 2100 | J8: =F8*G8 -> 0 | L8: =F8*I8 -> 0
B9: 1.5 | C9: 充电桩安装 | D9: 480kW直流充电桩（含终端1拖4） | E9: 台 | F9: 1 | G9: 500000 | I9: =7500*$M$3 -> 7875 | J9: =F9*G9 -> 500000 | L9: =F9*I9 -> 7875
B10: 2 | C10: 变配电装置
B11: 2.1 | C11: 开关柜
D12: 400V 并网柜（GGD柜，国内一线框架断路器630A） | E12: 面 | G12: 20000 | I12: =1000*$M$3 -> 1050 | J12: =F12*G12 -> 0 | L12: =F12*I12 -> 0
D13: 400V 并网柜（GGD柜，国内一线框架断路器1250A） | E13: 面 | G13: 25000 | I13: =1000*$M$3 -> 1050 | J13: =F13*G13 -> 0 | L13: =F13*I13 -> 0
D14: 400V 并网柜（GGD柜，250A*2塑断+500A塑断*2+50A塑断+25A*3塑断） | E14: 面 | F14: 1 | G14: 18000 | I14: =1000*$M$3 -> 1050 | J14: =F14*G14 -> 18000 | L14: =F14*I14 -> 1050
B15: 3 | C15: 租用平台管理系统
B16: 3.1 | C16: 充电云平台 | E16: 套 | G16: 2000 | I16: =500*$M$3 -> 525 | J16: =F16*G16 -> 0 | L16: =F16*I16 -> 0
B17: 3.2 | C17: 对接服务 | E17: 套 | G17: 20000 | I17: =500*$M$3 -> 525 | J17: =F17*G17 -> 0 | L17: =F17*I17 -> 0
B18: 3.3 | C18: 关口计量表 | D18: 0.2S级计量表 | E18: 套 | F18: 1 | G18: 2300 | I18: =100*$M$3 -> 105 | J18: =F18*G18 -> 2300 | L18: =F18*I18 -> 105
B19: 4 | C19: 电缆
B20: 4.1 | C20: 通信线缆
C21: 通信线缆 | D21: ZRC-kvvp2-22-0.45/0.75kV-2×4mm² | E21: m | H21: =11*$M$3 -> 11.55 | I21: =5*$M$3 -> 5.25 | K21: =F21*H21 -> 0 | L21: =F21*I21 -> 0
C22: RS485屏蔽双绞线 | D22: RVVP2*1.5mm² | E22: m | F22: 50 | H22: =5*$M$3 -> 5.25 | I22: =5*$M$3 -> 5.25 | K22: =F22*H22 -> 262.5 | L22: =F22*I22 -> 262.5
B23: 4.2 | C23: 低压交流电力电缆
D24: ZC-YJLHV22-0.6/1kV-3×150mm²+1×70mm² | E24: m | H24: =55.9*$M$3 -> 58.695 | I24: =20*$M$3 -> 21 | K24: =F24*H24 -> 0 | L24: =F24*I24 -> 0
D25: ZC-YJLHV22-0.6/1kV-3×240mm²+1×120mm² | E25: m | H25: =86.92*$M$3 -> 91.266 | I25: =20*$M$3 -> 21 | K25: =F25*H25 -> 0 | L25: =F25*I25 -> 0
D26: ZC-YJLHV22-0.6/1kV-3×300mm²+1×150mm² | E26: m | F26: 400 | H26: =111.65*$M$3 -> 117.2325 | I26: =20*$M$3 -> 21 | K26: =F26*H26 -> 46893 | L26: =F26*I26 -> 8400
D27: ZC-YJLHV22-0.6/1kV-3×240mm²+2×120mm² | E27: m | F27: 20 | H27: =102.32*$M$3 -> 107.436 | I27: =20*$M$3 -> 21 | K27: =F27*H27 -> 2148.72 | L27: =F27*I27 -> 420
D28: ZC-YJV22-0.6/1kV-4×240mm² | E28: m | F28: 80 | H28: =981.63*$M$3 -> 1030.7115 | I28: =20*$M$3 -> 21 | K28: =F28*H28 -> 82456.92 | L28: =F28*I28 -> 1680
D29: ZC-YJV22-0.6/1kV-1×70mm² | E29: m | F29: 80 | H29: =69.93*$M$3 -> 73.4265 | I29: =20*$M$3 -> 21 | K29: =F29*H29 -> 5874.12 | L29: =F29*I29 -> 1680
D30: ZC-YJV22-0.6/1kV-3×185mm²+2×95mm² | E30: m | F30: 20 | H30: =755.09*$M$3 -> 792.8445 | I30: =20*$M$3 -> 21 | K30: =F30*H30 -> 15856.89 | L30: =F30*I30 -> 420
B31: 4.3 | C31: 低压电缆头 | E31: 套 | F31: 32 | H31: =200*$M$3 -> 210 | I31: =200*$M$3 -> 210 | K31: =F31*H31 -> 6720 | L31: =F31*I31 -> 6720
B32: 4.4 | C32: 电缆保护管
C33: 软管 | D33: Φ50*3.7 PE材质 | E33: m | H33: =3*$M$3 -> 3.15 | I33: =8*$M$3 -> 8.4 | K33: =F33*H33 -> 0 | L33: =F33*I33 -> 0
C34: 不锈钢管 | D34: SC100，4.5mm厚 | E34: m | H34: =190*$M$3 -> 199.5 | I34: =15*$M$3 -> 15.75 | K34: =F34*H34 -> 0 | L34: =F34*I34 -> 0
C35: 不锈钢管 | D35: SC150，4.5mm厚 | E35: m | H35: =280*$M$3 -> 294 | I35: =15*$M$3 -> 15.75 | K35: =F35*H35 -> 0 | L35: =F35*I35 -> 0
C36: 热镀锌钢管 | D36: φ50 | E36: m | F36: 60 | H36: =32*$M$3 -> 33.6 | I36: =17*$M$3 -> 17.85 | K36: =F36*H36 -> 2016 | L36: =F36*I36 -> 1071
C37: 热镀锌钢管 | D37: φ100 | E37: m | F37: =40 -> 40 | H37: =60*$M$3 -> 63 | I37: =28*$M$3 -> 29.4 | K37: =F37*H37 -> 2520 | L37: =F37*I37 -> 1176
C38: 热镀锌钢管 | D38: φ125 | E38: m | H38: =85*$M$3 -> 89.25 | I38: =32*$M$3 -> 33.6 | K38: =F38*H38 -> 0 | L38: =F38*I38 -> 0
C39: 热镀锌钢管 | D39: φ150 | E39: m | H39: =110*$M$3 -> 115.5 | I39: =37*$M$3 -> 38.85 | K39: =F39*H39 -> 0 | L39: =F39*I39 -> 0
B40: 5 | C40: 接地及辅材
B41: 5.1 | C41: 接地
C42: 接地扁铁 | D42: 40X4 | E42: m | F42: 100 | H42: =20*$M$3 -> 21 | I42: =10*$M$3 -> 10.5 | K42: =F42*H42 -> 2100 | L42: =F42*I42 -> 1050
C43: 接地扁铁 | D43: 50X5 | E43: m | H43: =24*$M$3 -> 25.2 | I43: =12*$M$3 -> 12.6 | K43: =F43*H43 -> 0 | L43: =F43*I43 -> 0
C44: 黄绿接地线 | D44: BVR 1×4mm2 | E44: m | H44: =3.8*$M$3 -> 3.99 | I44: =5*$M$3 -> 5.25 | K44: =F44*H44 -> 0 | L44: =F44*I44 -> 0
C45: 黄绿接地线 | D45: BVR 1×16mm2 | E45: m | H45: =15*$M$3 -> 15.75 | I45: =5*$M$3 -> 5.25 | K45: =F45*H45 -> 0 | L45: =F45*I45 -> 0
B46: 5.2 | C46: 防火封堵 | D46: 有机防火堵料 | E46: t | F46: 0.4 | I46: =7000*$M$3 -> 7350 | L46: =F46*I46 -> 2940
B47: 5.3 | C47: 灭火器箱 | D47: 手提式灭火器，含不锈钢防护罩 | E47: 套 | F47: 4 | I47: =500*$M$3 -> 525 | L47: =F47*I47 -> 2100
B48: 6 | C48: EHS
B49: 6.1 | C49: 地锁 | D49: 防撞款 | E49: 个 | I49: =450*$M$3 -> 472.5 | L49: =F49*I49 -> 0
B50: 6.2 | C50: 车位划线 | E50: m | I50: =10*$M$3 -> 10.5 | L50: =F50*I50 -> 0
B51: 6.3 | C51: 车档 | D51: 蜂窝状 | E51: 对 | I51: =85*$M$3 -> 89.25 | L51: =F51*I51 -> 0
B52: 6.4 | C52: 围栏 | D52: 碳钢栅栏1.5米高，Q235B材质，厚度2.0mm，立柱预埋混凝土安装 | E52: m | F52: 45 | I52: =120*$M$3 -> 126 | L52: =F52*I52 -> 5670
B53: 7 | C53: 设备基础
B54: 7.1 | C54: 电缆井 | D54: 内径尺寸：1200*1200*1400mm | E54: 个 | I54: =3000*$M$3 -> 3150 | L54: =F54*I54 -> 0
B55: 7.2 | C55: 并网配电柜基础 | E55: 个 | F55: 1 | I55: =2000*$M$3 -> 2100 | L55: =F55*I55 -> 2100
B56: 7.3 | C56: 充电桩基础
C57: 直流充电桩基础 | D57: 60KW | E57: 个 | I57: =1500*$M$3 -> 1575 | L57: =F57*I57 -> 0
C58: 直流充电桩基础 | D58: 132kW直流充电桩 V2G | E58: 个 | F58: 1 | I58: =2000*$M$3 -> 2100 | L58: =F58*I58 -> 2100
C59: 直流充电桩基础 | D59: 240KW | E59: 个 | I59: =3000*$M$3 -> 3150 | L59: =F59*I59 -> 0
C60: 充电主机+冷源基础 | D60: 480KW | E60: 个 | F60: 1 | I60: =6000*$M$3 -> 6300 | L60: =F60*I60 -> 6300
B61: 8 | C61: 电缆敷设
B62: 8.1 | C62: 破路 | E62: m | F62: 20 | I62: =230*$M$3 -> 241.5 | L62: =F62*I62 -> 4830
B63: 8.2 | C63: 电缆沟 | D63: 不含管材，砖砌800*800 | E63: m | I63: =500*$M$3 -> 525 | L63: =F63*I63 -> 0
B64: 8.3 | C64: 直埋 | D64: 铺砂盖转 | E64: m | F64: 20 | I64: =40*$M$3 -> 42 | L64: =F64*I64 -> 840
B65: 9 | C65: 绿化修复 | D65: 草皮 | E65: ㎡ | I65: =40*$M$3 -> 42 | L65: =F65*I65 -> 0
B66: 10 | C66: 地面重做 | D66: 200mm沥青（含原场地拆除） | E66: ㎡ | F66: 1300 | I66: =150*$M$3 -> 157.5 | L66: =F66*I66 -> 204750
B67: 11 | C67: 充电桩调试
B68: 11.1 | C68: 超充调试 | E68: 项 | I68: =2000*$M$3 -> 2100 | L68: =F68*I68 -> 0
B69: 11.2 | C69: 直流桩调试 | E69: 项 | I69: =200*$M$3 -> 210 | L69: =F69*I69 -> 0
B70: 11.3 | C70: 交流桩调试 | E70: 项 | I70: =100*$M$3 -> 105 | L70: =F70*I70 -> 0
B71: 汇总 | J71: =SUM(J5:J70) -> 618300 | K71: =SUM(K5:K70) -> 166848.15 | L71: =SUM(L5:L70)*1.1 -> 291048.45
A72: 额外要求成本 | B72: 12 | C72: 额外要求成本
B73: 12.1 | L73: =F73*I73 -> 0

Sheet 调整系数
B1: 建安费（含主材）调整系数
B2: 光伏项目容量 | C2: ≤1MW | D2: 1MW＜x≤3MW | E2: 3MW＜x≤6MW | F2: ＞6MW
B3: 调整系数 | C3: 1.1 | D3: 1.05 | E3: 1 | F3: 0.95
B5: 储能项目容量 | C5: ≤2MWh | D5: 2MWh＜x≤6MWh | E5: 6MWh＜x≤12MWh | F5: ＞12MWh
B6: 调整系数 | C6: 1.1 | D6: 1.05 | E6: 1 | F6: 0.95
B8: 充电桩项目容量 | C8: ≤0.5MW | D8: 0.5MW＜x≤2.5MW | E8: 2.5MW＜x≤5MWh | F8: ＞5MWh
B9: 调整系数 | C9: 1.1 | D9: 1.05 | E9: 1 | F9: 0.95
B11: 地区 | C11: 一类地区 | D11: 二类地区 | E11: 三类地区 | F11: 四类地区
B12: 调整系数 | C12: 1.1 | D12: 1 | E12: 1.05 | F12: 1.1
B13: 一类地区 | C13: 北京，天津，上海，浙江，江苏，广东，深圳
B14: 二类地区 | C14: 河北，山西，陕西，山东，辽宁，安徽，四川，重庆，湖南，湖北，福建，江西，河南，广西
B15: 三类地区 | C15: 甘肃，宁夏，青海，黑龙江，吉林，贵州，海南，云南
B16: 四类地区 | C16: 内蒙古，新疆，西藏

Sheet 微网方案
A1: 沈阳某项目微网控制器策略方案
A2: 版本：V2.0 | B2: 安科瑞DTSD1352电表(CT160) 地址是204
A3: 适用范围：仅可控制储能PCS与光伏逆变器，充电桩及V2G桩均视为不可控负载
A5: 一、系统参数与安全红线（硬约束）
A6: 1.1 设备配置
A7: 设备 | B7: 关键参数 | C7: 可控性
A8: 变压器 | B8: 500kVA | C8: ——
A9: 储能系统 | B9: 容量262kWh，PCS额定功率 125kW（充放电） | C9: 完全可控
A10: 光伏 | B10: （光伏功率组件：42块620wp）26kW，逆变器：30KW，支持功率限发/关断指令 | C10: 完全可控
A11: 分体式充电桩 | B11: 总功率480kW，4终端动态分配 | C11: 不可控
A12: V2G充电桩 | B12: 额定120kW（一般车端最大放电功率 40kW，充电120KW）充放均不可控 | C12: 不可控
A14: 1.2 核心安全红线（优先级最高，任何时刻必须满足）
A15: 安全指标 | B15: 设定值 | C15: 说明
A16: 防逆流硬底线 | B16: 电网关口功率 Pgrid≥0Pgrid​≥0 kW，绝对不允许反向电流
A17: 控制响应时间 | B17: 从异常检测到功率指令下发 ≤100ms，3秒内完成闭环 | C17: 本地高速采样与直连通讯
A19: 二、控制架构与优先级
A20: 控制器实时采集 Ppv,Pload,SOC,PgridPpv​,Pload​,SOC,Pgrid​，每 100ms 执行一次策略循环。所有模式遵循以下优先级：
A21: 防逆流安全链 → 防超需安全链 → 分时经济调度
A22: 安全链一旦触发，直接越过经济调度，向储能和光伏下发强制指令。当电网功率恢复到安全区间后，无故障保持5秒，安全链退出，交回经济调度。
A25: 四、沈阳分时电价导入
A26: 根据辽宁省分时电价政策，配置如下时段表（示例价格，可通过参数更新）：
A27: 时段类型 | B27: 时间段 | C27: 执行月份
A28: 谷段 | B28: 22:00-次日5:00 | C28: 全年
A29: 平段 | B29: 5:00-7:30, 10:30-16:00, 21:00-22:00 | C29: 全年
A30: 高峰 | B30: 7:30-10:30, 16:00-18:00, 20:00-21:00 | C30: 全年
A31: 尖峰 | B31: 18:00-20:00 | C31: 7,8,12,1月执行，其余月份按高峰计价
A33: 特殊情况：
A34: 夏季/冬季尖峰（执行月份：1月、7月、8月、12月） | B34: 执行时间：18：00 - 20：00；逻辑：在这4个月份里，原本属于“高峰”的 18：00-20：00 升级为“尖峰”。
A35: 7月和8月的午间谷电（“深谷”） | B35: 辽宁省为了促进光伏消纳，在光伏大发的中午时段设置了更便宜的电价（通常称为深谷或低谷延伸）。 执行月份：7月、8月 具体时段：11：30 - 13：30 逻辑：这2个月份里，原本属于“平段”的 11：30-13：30 调整为“谷段”电价（或平时段电价下浮更大比例，具体看细则）。对于您的策略：如果此时光伏大发，优先用光伏；如果光伏不足，这2小时的电价比平时便宜，储能的充放电策略需要留意。
A36: 控制器需支持远程更新电价、时段及尖峰执行日期。
A38: 时间范围 | B38: 默认电价类型 | C38: 特殊规则触发条件
A39: 00：00 - 05：00 | B39: 谷段 | C39: 无
A40: 05：00 - 07：30 | B40: 平段 | C40: 无
A41: 07：30 - 10：30 | B41: 高峰 | C41: 无
A42: 10：30 - 11：30 | B42: 平段 | C42: 无
A43: 11：30 - 13：30 | B43: 平段 | C43: 若月份=7或8，调整为谷段电价
A44: 13：30 - 16：00 | B44: 平段 | C44: 无
A45: 16：00 - 18：00 | B45: 高峰 | C45: 无
A46: 18：00 - 20：00 | B46: 高峰 | C46: 若月份=1、7、8、12，调整为尖峰电价
A47: 20：00 - 21：00 | B47: 高峰 | C47: 无
A48: 21：00 - 22：00 | B48: 平段 | C48: 无
A49: 22：00 - 24：00 | B49: 谷段 | C49: 无
A52: 六、储能全周期管理及约束
A53: 充电窗口： | B53: 仅谷电时段及平电时段光伏有余时。
A54: 放电窗口： | B54: 仅峰电、尖峰时段，以及安全链触发时。
A55: SOC保持： | B55: 期望谷电结束时SOC达到70%（假设值）以上；白天由光伏补电
A56: 禁用场景： | B56: 峰电、尖峰时段绝对禁止从电网充电；平电时段禁止用网电充电。
A57: V2G耦合： | B57: V2G放电会在任何时段自动被储能吸收，不产生逆流。 | C57: 注意储能需要留有SOC余量满足光伏和V2G存在的补电可能
